vrpbap/__about__.py
vrpbap/__init__.py
vrpbap/main.py
vrpbap-0.0.1.dist-info/METADATA
vrpbap-0.0.1.dist-info/WHEEL
vrpbap-0.0.1.dist-info/licenses/LICENSE.txt
vrpbap-0.0.1.dist-info/RECORD
