Metadata-Version: 2.4
Name: vrpbap
Version: 0.0.1
Project-URL: Documentation, https://github.com/Kurorororo/vrpbap#readme
Project-URL: Issues, https://github.com/Kurorororo/vrpbap/issues
Project-URL: Source, https://github.com/Kurorororo/vrpbap
Author-email: Ryo Kuroiwa <kuroiwa@nii.ac.jp>
License-Expression: MIT
License-File: LICENSE.txt
Keywords: VRP,branch and price,column generation,combinatorial optimization,integer linear programming,vehicle routing
Classifier: Development Status :: 4 - Beta
Classifier: Programming Language :: Python
Classifier: Programming Language :: Python :: 3.8
Classifier: Programming Language :: Python :: 3.9
Classifier: Programming Language :: Python :: 3.10
Classifier: Programming Language :: Python :: 3.11
Classifier: Programming Language :: Python :: 3.12
Classifier: Programming Language :: Python :: Implementation :: CPython
Classifier: Programming Language :: Python :: Implementation :: PyPy
Requires-Python: >=3.8
Requires-Dist: pyscipopt>=4.0.0
